PyOptik/__init__.py
PyOptik/__main__.py
PyOptik/_version.py
PyOptik/directories.py
PyOptik/material_bank.py
PyOptik/material_type.py
PyOptik/utils.py
PyOptik/data/__init__.py
PyOptik/data/sellmeier/BAF10.yml
PyOptik/data/sellmeier/BAK1.yml
PyOptik/data/sellmeier/BK7.yml
PyOptik/data/sellmeier/FK51A.yml
PyOptik/data/sellmeier/LASF9.yml
PyOptik/data/sellmeier/SF10.yml
PyOptik/data/sellmeier/SF11.yml
PyOptik/data/sellmeier/SF5.yml
PyOptik/data/sellmeier/ZBLAN.yml
PyOptik/data/sellmeier/acetone.yml
PyOptik/data/sellmeier/acetylene.yml
PyOptik/data/sellmeier/air.yml
PyOptik/data/sellmeier/argon.yml
PyOptik/data/sellmeier/cellulose.yml
PyOptik/data/sellmeier/crown.yml
PyOptik/data/sellmeier/ethane.yml
PyOptik/data/sellmeier/ethanol.yml
PyOptik/data/sellmeier/ethylene.yml
PyOptik/data/sellmeier/example_sellmeier.yml
PyOptik/data/sellmeier/flint.yml
PyOptik/data/sellmeier/fused_silica.yml
PyOptik/data/sellmeier/germanium.yml
PyOptik/data/sellmeier/glycerol.yml
PyOptik/data/sellmeier/lithium_niobate.yml
PyOptik/data/sellmeier/methane.yml
PyOptik/data/sellmeier/methanol.yml
PyOptik/data/sellmeier/polycarbonate.yml
PyOptik/data/sellmeier/polystyren.yml
PyOptik/data/sellmeier/polystyrene.yml
PyOptik/data/sellmeier/propanol.yml
PyOptik/data/sellmeier/pvc.yml
PyOptik/data/sellmeier/soda_lime_glass.yml
PyOptik/data/sellmeier/test_sellmeier_file.yml
PyOptik/data/sellmeier/water.yml
PyOptik/data/tabulated/aluminium.yml
PyOptik/data/tabulated/bismuth.yml
PyOptik/data/tabulated/calcium.yml
PyOptik/data/tabulated/chromium.yml
PyOptik/data/tabulated/copper.yml
PyOptik/data/tabulated/example_tabulated.yml
PyOptik/data/tabulated/gold.yml
PyOptik/data/tabulated/iron.yml
PyOptik/data/tabulated/lead.yml
PyOptik/data/tabulated/magnesium.yml
PyOptik/data/tabulated/nickel.yml
PyOptik/data/tabulated/paladium.yml
PyOptik/data/tabulated/polyetylene.yml
PyOptik/data/tabulated/pva.yml
PyOptik/data/tabulated/rhodium.yml
PyOptik/data/tabulated/silicon.yml
PyOptik/data/tabulated/silver.yml
pyoptik-2.0.6.dist-info/licenses/LICENSE
pyoptik-2.0.6.dist-info/METADATA
pyoptik-2.0.6.dist-info/WHEEL
pyoptik-2.0.6.dist-info/top_level.txt
pyoptik-2.0.6.dist-info/RECORD
