Metadata-Version: 2.4
Name: PyOptik
Version: 2.0.6
Summary: A package for refractive index values.
Author-email: Martin Poinsinet de Sivry-Houle <martin.poinsinet.de.sivry@gmail.com>
License: MIT License
Keywords: refractive index,optics
Classifier: Programming Language :: Python
Classifier: Programming Language :: Python :: 3
Classifier: Programming Language :: Python :: Implementation :: CPython
Classifier: Development Status :: 4 - Beta
Classifier: Topic :: Scientific/Engineering :: Physics
Classifier: Intended Audience :: Science/Research
Requires-Python: >=3.10
License-File: LICENSE
Requires-Dist: pint~=0.24
Requires-Dist: numpy
Requires-Dist: matplotlib~=3.8
Requires-Dist: requests~=2.31
Requires-Dist: pyyaml~=6.0
Requires-Dist: MPSPlots
Requires-Dist: tabulate~=0.9
Requires-Dist: TypedUnit
Provides-Extra: testing
Requires-Dist: pytest<9.0,>=7.4; extra == "testing"
Requires-Dist: pytest-cov<6,>=2; extra == "testing"
Requires-Dist: pytest-json-report~=1.5; extra == "testing"
Requires-Dist: coverage~=7.6; extra == "testing"
Provides-Extra: documentation
Requires-Dist: numpydoc==1.6.0; extra == "documentation"
Requires-Dist: sphinx>=5.1.1; extra == "documentation"
Requires-Dist: sphinx-gallery==0.15.0; extra == "documentation"
Requires-Dist: sphinx-rtd-theme==2.0.0; extra == "documentation"
Requires-Dist: pydata-sphinx-theme==0.14.1; extra == "documentation"
Provides-Extra: dev
Requires-Dist: flake8==7.1.1; extra == "dev"
Dynamic: license-file
